drip/__init__.py
drip/main.py
pydrip/__init__.py
pydrip-0.2.0.dist-info/LICENSE
pydrip-0.2.0.dist-info/METADATA
pydrip-0.2.0.dist-info/WHEEL
pydrip-0.2.0.dist-info/top_level.txt
pydrip-0.2.0.dist-info/RECORD
