Metadata-Version: 2.1
Name: pydrip
Version: 0.2.0
Summary: A Python 3 client for the Drip API.
Home-page: https://github.com/flypaperplanes/pydrip
Author: Matthew Clarkson
Author-email: mpclarkson@gmail.com
License: UNKNOWN
Platform: UNKNOWN
Classifier: Programming Language :: Python :: 3
Classifier: License :: OSI Approved :: MIT License
Classifier: Operating System :: OS Independent
Requires-Dist: requests
